optimfactory/__init__.py
optimfactory/combo.py
optimfactory/initialization.py
optimfactory/param_group.py
optimfactory/utils.py
optimfactory-0.0.1.dist-info/licenses/LICENSE
optimfactory-0.0.1.dist-info/METADATA
optimfactory-0.0.1.dist-info/WHEEL
optimfactory-0.0.1.dist-info/top_level.txt
optimfactory-0.0.1.dist-info/RECORD
