Metadata-Version: 2.4
Name: optimfactory
Version: 0.0.1
Summary: Pytorch optimizer factory with modern init technique
Author-email: "Shih-Ying Yeh(KohakuBlueLeaf)" <apolloyeh0123@gmail.com>
License: Apache-2.0
Project-URL: Homepage, https://github.com/KohakuBlueleaf/KohakuRAG
Requires-Python: >=3.10
License-File: LICENSE
Requires-Dist: torch
Requires-Dist: torchvision
Provides-Extra: dev
Dynamic: license-file
